<xml3d xmlns="http://www.xml3d.org/2009/xml3d">
<defs>
<transform translation="136193 0 89748" id="tf"/>
</defs>
<asset id="plane">
<assetmesh shader="../../shared/basic-6a80933fd1de8af147fc588b3288caf16a53cb1c.xml#shader_surface" type="triangles">
<data src="../../shared/basic-6a80933fd1de8af147fc588b3288caf16a53cb1c.xml#mesh_ground"/>
<texture name="diffuseTexture">
<img src="89748-23be3c0530b7f225c6740044ab9f7d8a53e01745.png"/>
</texture>
</assetmesh>
</asset>
<asset id="buildings">
<assetmesh shader="../../shared/basic-6a80933fd1de8af147fc588b3288caf16a53cb1c.xml#shader_building" type="triangles">
<data compute="dataflow['../../shared/basic-6a80933fd1de8af147fc588b3288caf16a53cb1c.xml#dataflow_extrude']">
<float2 name="contour">
-0.088903964438941 0.48277889071323 0.54380970666534 0.072041172723402 0.76488448001328 0.41261234378908 0.132170808909 0.82334752180032 -0.088903964438941 0.48277889071323</float2>
<float name="height">
15.368327235509</float>
</data>
</assetmesh>
</asset>
</xml3d>