<xml3d xmlns="http://www.xml3d.org/2009/xml3d">
<defs>
<transform translation="129806 0 91061" id="tf"/>
</defs>
<asset id="plane">
<assetmesh shader="../../shared/basic-6a80933fd1de8af147fc588b3288caf16a53cb1c.xml#shader_surface" type="triangles">
<data src="../../shared/basic-6a80933fd1de8af147fc588b3288caf16a53cb1c.xml#mesh_ground"/>
<texture name="diffuseTexture">
<img src="91061-7c976e0ccc2508be16985a1f897730c9fb88cc1e.png"/>
</texture>
</assetmesh>
</asset>
<asset id="buildings">
<assetmesh shader="../../shared/basic-6a80933fd1de8af147fc588b3288caf16a53cb1c.xml#shader_building" type="triangles">
<data compute="dataflow['../../shared/basic-6a80933fd1de8af147fc588b3288caf16a53cb1c.xml#dataflow_extrude']">
<float2 name="contour">
0.52532622222498 -0.15751077208552 0.5114908444375 -0.032219542714301 0.21439431111503 -0.065993672644254 0.19546168889792 0.099608318210812 0.49328640000022 0.1344718329201 0.47872284443292 0.2554044816643 0.56464782223338 0.26520982013608 0.5894058666745 0.047313005517935 0.92946488888992 0.086534494592343 0.9323776000092 0.064744781819172 0.95567928887613 0.068013239273569 0.95713564445032 0.050581463976414 0.99354453332489 0.05493940829183 1.0110207999969 -0.1019468010345 0.94985386666667 -0.10957322517061 0.95859200000996 -0.18583752360428 0.88067697777296 -0.19564294091833 0.87849244444806 -0.17494261747925 0.87193884444423 -0.11828913976206 0.6119793777907 -0.14770536142169 0.52532622222498 -0.15751077208552</float2>
<float name="height">
15.694621194012</float>
</data>
</assetmesh>
</asset>
</xml3d>