<xml3d xmlns="http://www.xml3d.org/2009/xml3d">
<defs>
<transform translation="129817 0 91057" id="tf"/>
</defs>
<asset id="plane">
<assetmesh shader="../../shared/basic-6a80933fd1de8af147fc588b3288caf16a53cb1c.xml#shader_surface" type="triangles">
<data src="../../shared/basic-6a80933fd1de8af147fc588b3288caf16a53cb1c.xml#mesh_ground"/>
<texture name="diffuseTexture">
<img src="91057-dd8b5967542fbc74c47e6d4c5074c6e865fdfd79.png"/>
</texture>
</assetmesh>
</asset>
<asset id="buildings">
<assetmesh shader="../../shared/basic-6a80933fd1de8af147fc588b3288caf16a53cb1c.xml#shader_building" type="triangles">
<data compute="dataflow['../../shared/basic-6a80933fd1de8af147fc588b3288caf16a53cb1c.xml#dataflow_extrude']">
<float2 name="contour">
0.61620195556316 0.56738616677467 0.64023182222445 0.47259490724537 0.53173333333689 0.44862467827625 0.50770346667559 0.54123686980165 0.61620195556316 0.56738616677467</float2>
<float name="height">
13.174434012349</float>
</data>
</assetmesh>
<assetmesh shader="../../shared/basic-6a80933fd1de8af147fc588b3288caf16a53cb1c.xml#shader_building" type="triangles">
<data compute="dataflow['../../shared/basic-6a80933fd1de8af147fc588b3288caf16a53cb1c.xml#dataflow_extrude']">
<float2 name="contour">
0.24992853333242 0.9432809636055 0.2528412444517 0.92584821714263 0.30454186667339 0.93674368431675 0.32201813333086 0.85175898422312 0.22589866665658 0.83105756342411 0.2062378666742 0.91604229487712 0.21424782222311 0.91822138885618 0.2098787555442 0.93456459103618 0.24992853333242 0.9432809636055</float2>
<float name="height">
14.657934286938</float>
</data>
</assetmesh>
<assetmesh shader="../../shared/basic-6a80933fd1de8af147fc588b3288caf16a53cb1c.xml#shader_building" type="triangles">
<data compute="dataflow['../../shared/basic-6a80933fd1de8af147fc588b3288caf16a53cb1c.xml#dataflow_extrude']">
<float2 name="contour">
0.18075164445327 0.42901266517583 0.20478151111456 0.32877337990794 0.12759466665739 0.31243000121322 0.10429297779046 0.41049020204809 0.17492622221471 0.4279231086839 0.18075164445327 0.42901266517583</float2>
<float name="height">
17.52624534421</float>
</data>
</assetmesh>
<assetmesh shader="../../shared/basic-6a80933fd1de8af147fc588b3288caf16a53cb1c.xml#shader_building" type="triangles">
<data compute="dataflow['../../shared/basic-6a80933fd1de8af147fc588b3288caf16a53cb1c.xml#dataflow_extrude']">
<float2 name="contour">
0.52809244443779 0.31460911864997 0.60892017777951 0.31460911864997 0.6103765333246 0.31896735326154 0.60964835554478 0.33095249670441 0.64532906668319 0.3320420550881 0.6475136000081 0.31569867732469 0.68392248888267 0.31678823599941 0.68392248888267 0.30480308950064 0.70503964445379 0.30371353062219 0.7072241777787 0.22199655292206 0.67882524445304 0.22199655292206 0.68028159999812 0.1980262168654 0.64460088887427 0.1980262168654 0.64532906668319 0.20783226467029 0.60964835554478 0.20783226467029 0.6103765333246 0.23289215681143 0.58561848888348 0.23289215681143 0.58489031110366 0.22635479472228 0.56450133334147 0.22635479472228 0.56450133334147 0.1784141161188 0.53901511112053 0.17950367745652 0.52736426665797 0.20456358225783 0.52809244443779 0.31460911864997</float2>
<float name="height">
11.360519547649</float>
</data>
</assetmesh>
<assetmesh shader="../../shared/basic-6a80933fd1de8af147fc588b3288caf16a53cb1c.xml#shader_building" type="triangles">
<data compute="dataflow['../../shared/basic-6a80933fd1de8af147fc588b3288caf16a53cb1c.xml#dataflow_extrude']">
<float2 name="contour">
0.89290951112343 1.0326237042027 0.90528853332216 1.0282655250194 0.88125866666087 0.94654960295884 0.86523875554849 0.95199733480695 0.89290951112343 1.0326237042027</float2>
<float name="height">
19.87217404408</float>
</data>
</assetmesh>
<assetmesh shader="../../shared/basic-6a80933fd1de8af147fc588b3288caf16a53cb1c.xml#shader_building" type="triangles">
<data compute="dataflow['../../shared/basic-6a80933fd1de8af147fc588b3288caf16a53cb1c.xml#dataflow_extrude']">
<float2 name="contour">
0.73999217778328 0.67634143964096 0.75164302223129 0.70793842917192 0.77858559999731 0.69813246879494 0.77421653333295 0.68505785232992 0.73999217778328 0.67634143964096</float2>
<float name="height">
11.88954857266</float>
</data>
</assetmesh>
<assetmesh shader="../../shared/basic-6a80933fd1de8af147fc588b3288caf16a53cb1c.xml#shader_building" type="triangles">
<data compute="dataflow['../../shared/basic-6a80933fd1de8af147fc588b3288caf16a53cb1c.xml#dataflow_extrude']">
<float2 name="contour">
0.10429297779046 0.41049020204809 0.075894044450251 0.40286330369418 0.043854222225491 0.53578909806674 0.071524977785884 0.54232642409625 0.10429297779046 0.41049020204809</float2>
<float name="height">
16.531214931296</float>
</data>
</assetmesh>
<assetmesh shader="../../shared/basic-6a80933fd1de8af147fc588b3288caf16a53cb1c.xml#shader_building" type="triangles">
<data compute="dataflow['../../shared/basic-6a80933fd1de8af147fc588b3288caf16a53cb1c.xml#dataflow_extrude']">
<float2 name="contour">
0.53828693332616 0.737356299971 0.51862613332924 0.82343072223011 0.63950364444463 0.85175898422312 0.66134897776647 0.76350550552888 0.59799751111132 0.74934135403601 0.59945386667096 0.74498315286473 0.56668586666638 0.73844585043844 0.56522951112129 0.74389360251371 0.53828693332616 0.737356299971</float2>
<float name="height">
11.76070662763</float>
</data>
</assetmesh>
<assetmesh shader="../../shared/basic-6a80933fd1de8af147fc588b3288caf16a53cb1c.xml#shader_building" type="triangles">
<data compute="dataflow['../../shared/basic-6a80933fd1de8af147fc588b3288caf16a53cb1c.xml#dataflow_extrude']">
<float2 name="contour">
0.39556408888893 0.74607270318666 0.50042168889195 0.77222190465545 0.51935431110905 0.69159516095533 0.41449671110604 0.66653547374881 0.39993315556785 0.72863989541656 0.39556408888893 0.74607270318666</float2>
<float name="height">
13.482514630762</float>
</data>
</assetmesh>
<assetmesh shader="../../shared/basic-6a80933fd1de8af147fc588b3288caf16a53cb1c.xml#shader_building" type="triangles">
<data compute="dataflow['../../shared/basic-6a80933fd1de8af147fc588b3288caf16a53cb1c.xml#dataflow_extrude']">
<float2 name="contour">
1.0567495111172 0.97705689445138 1.0363605333259 0.91822138885618 1.0261660444376 0.88335587494657 0.97228088887641 0.90296772916918 0.97592177777551 0.91386320081074 0.96208640000259 0.91822138885618 0.95917368889786 0.91059455953655 0.94606648889021 0.91495274784393 0.94897920000949 0.92257957658148 0.88125866666087 0.94654960295884 0.90528853332216 1.0282655250194 1.0567495111172 0.97705689445138</float2>
<float name="height">
15.282917607242</float>
</data>
</assetmesh>
<assetmesh shader="../../shared/basic-6a80933fd1de8af147fc588b3288caf16a53cb1c.xml#shader_building" type="triangles">
<data compute="dataflow['../../shared/basic-6a80933fd1de8af147fc588b3288caf16a53cb1c.xml#dataflow_extrude']">
<float2 name="contour">
0.75164302223129 0.70793842917192 0.77130382222822 0.76350550552888 0.79751822221442 0.75478910503443 0.77858559999731 0.69813246879494 0.75164302223129 0.70793842917192</float2>
<float name="height">
11.447170670818</float>
</data>
</assetmesh>
<assetmesh shader="../../shared/basic-6a80933fd1de8af147fc588b3288caf16a53cb1c.xml#shader_building" type="triangles">
<data compute="dataflow['../../shared/basic-6a80933fd1de8af147fc588b3288caf16a53cb1c.xml#dataflow_extrude']">
<float2 name="contour">
0.10429297779046 0.41049020204809 0.071524977785884 0.54232642409625 0.14215822222468 0.55975928975386 0.17492622221471 0.4279231086839 0.10429297779046 0.41049020204809</float2>
<float name="height">
12.983838870648</float>
</data>
</assetmesh>
<assetmesh shader="../../shared/basic-6a80933fd1de8af147fc588b3288caf16a53cb1c.xml#shader_building" type="triangles">
<data compute="dataflow['../../shared/basic-6a80933fd1de8af147fc588b3288caf16a53cb1c.xml#dataflow_extrude']">
<float2 name="contour">
0.41959395555023 0.64583398457034 0.32056177778577 0.62186382967047 0.29944462221465 0.70358022478467 0.39993315556785 0.72863989541656 0.41449671110604 0.66653547374881 0.41959395555023 0.64583398457034</float2>
<float name="height">
11.410821360262</float>
</data>
</assetmesh>
<assetmesh shader="../../shared/basic-6a80933fd1de8af147fc588b3288caf16a53cb1c.xml#shader_building" type="triangles">
<data compute="dataflow['../../shared/basic-6a80933fd1de8af147fc588b3288caf16a53cb1c.xml#dataflow_extrude']">
<float2 name="contour">
0.78659555556078 0.64801308905589 0.8135381333268 0.53796820683056 0.73780764444382 0.51944577967515 0.71159324445762 0.62949069825117 0.78659555556078 0.64801308905589</float2>
<float name="height">
16.043677146567</float>
</data>
</assetmesh>
<assetmesh shader="../../shared/basic-6a80933fd1de8af147fc588b3288caf16a53cb1c.xml#shader_building" type="triangles">
<data compute="dataflow['../../shared/basic-6a80933fd1de8af147fc588b3288caf16a53cb1c.xml#dataflow_extrude']">
<float2 name="contour">
0.85358791111503 0.026964884978952 0.7705756444484 0.023696192030911 0.7705756444484 0.010621418303344 0.65406720001192 0.0084422890649876 0.65406720001192 -0.022065529308748 0.62858097776189 -0.023155094546382 0.61911466665333 -0.002453358436469 0.62057102222752 0.11304039745301 0.65770808888192 0.11412996004219 0.65843626666174 0.10214477026602 0.67955342223286 0.10323433307349 0.67955342223286 0.11521952261683 0.70285511111433 0.11521952261683 0.70285511111433 0.12720470962813 0.77494471109821 0.12829427195538 0.77567288887803 0.11521952261683 0.79533368888951 0.11630908519146 0.79533368888951 0.12829427195538 0.81936355556536 0.12938383425353 0.81936355556536 0.14136901823804 0.85213155555539 0.14027945615817 0.85358791111503 0.026964884978952</float2>
<float name="height">
11.410928532207</float>
</data>
</assetmesh>
<assetmesh shader="../../shared/basic-6a80933fd1de8af147fc588b3288caf16a53cb1c.xml#shader_building" type="triangles">
<data compute="dataflow['../../shared/basic-6a80933fd1de8af147fc588b3288caf16a53cb1c.xml#dataflow_extrude']">
<float2 name="contour">
0.35260160001053 0.13810033194022 0.37663146667182 0.037860526761506 0.29798826666956 0.019337934456416 0.27468657777354 0.11957777274074 0.35260160001053 0.13810033194022</float2>
<float name="height">
13.928710238044</float>
</data>
</assetmesh>
</asset>
</xml3d>