<xml3d xmlns="http://www.xml3d.org/2009/xml3d">
<defs>
<transform translation="129810 0 91060" id="tf"/>
</defs>
<asset id="plane">
<assetmesh shader="../../shared/basic-6a80933fd1de8af147fc588b3288caf16a53cb1c.xml#shader_surface" type="triangles">
<data src="../../shared/basic-6a80933fd1de8af147fc588b3288caf16a53cb1c.xml#mesh_ground"/>
<texture name="diffuseTexture">
<img src="91060-2588236454fb4313af0884cfd303db6c2ae80fb5.png"/>
</texture>
</assetmesh>
</asset>
<asset id="buildings">
<assetmesh shader="../../shared/basic-6a80933fd1de8af147fc588b3288caf16a53cb1c.xml#shader_building" type="triangles">
<data compute="dataflow['../../shared/basic-6a80933fd1de8af147fc588b3288caf16a53cb1c.xml#dataflow_extrude']">
<float2 name="contour">
0.46768071111001 0.45680838252883 0.49171057778585 0.38381199183641 0.47933155554347 0.35875350747665 0.44219448888907 0.37836449619499 0.4207132444426 0.37128275106079 0.39631928889139 0.36311150554684 0.37738666667428 0.32606851102901 0.35335679999844 0.33805301193206 0.20772124444193 0.78583571058698 0.23029475555813 0.79346214895486 0.26306275556271 0.77276181383058 0.30966613334022 0.78801469306927 0.32350151109858 0.8239678920072 0.95992888888577 1.0320601967833 0.94536533333303 1.0767291248922 1.0087168000027 1.0974293478212 1.0116295111075 1.0887134654186 1.0968263111135 1.1159505934338 1.0939135999943 1.12575595628 1.157265066664 1.1464561611065 1.1725567999965 1.1006978033693 1.3931946666708 1.1726037773333 1.4354289777839 1.0429550605477 1.4732942222327 0.92746939664357 1.514800355566 0.79890960427292 0.46768071111001 0.45680838252883</float2>
<float name="height">
15.386488742841</float>
</data>
</assetmesh>
<assetmesh shader="../../shared/basic-6a80933fd1de8af147fc588b3288caf16a53cb1c.xml#shader_building" type="triangles">
<data compute="dataflow['../../shared/basic-6a80933fd1de8af147fc588b3288caf16a53cb1c.xml#dataflow_extrude']">
<float2 name="contour">
0.2048085333372 0.79455164005049 0.12033991112548 0.76731435596594 0.11305813334184 0.79019367549336 0.19752675555355 0.81743094846024 0.2048085333372 0.79455164005049</float2>
<float name="height">
17.240830341932</float>
</data>
</assetmesh>
</asset>
</xml3d>